[
    {
        "name": "DiamondMon",
        "id": 451802211757064192,
        "rank": "Helper"
    },
    {
        "name": "Digit1740",
        "id": 511155292461989889,
        "rank": "Helper"
    },
    {
        "name": "DorkOrc",
        "id": 336123112187887619,
        "rank":"Admin"
    },
    {
        "name": "Echos",
        "id": 915455249899221033,
        "rank": "Helper"
    },
    {
        "name": "gabi",
        "id": 361979580036284428,
        "rank": "Helper"
    },
    {
        "name": "GGIS",
        "id": 918213403376492574,
        "rank": "Helper"
    },
    {
        "name": "Hawkan",
        "id": 497214837374320670,
        "rank": "SR.Moderator"
    },
    {
        "name": "KittyAcel (T/T)",
        "id": 423288503422418946,
        "rank":"SR.Moderator"
    },
    {
        "name": "KodaDaCod",
        "id": 202863749315559424,
        "rank": "Helper"
    },
    {
        "name": "L0Lluc007",
        "id": 351039332238491648,
        "rank": "Helper"
    },
    {
        "name": "Mandalay",
        "id": 437805206143762434,
        "rank":"SR.Moderator"
    },
    {
        "name": "MaroonAngel",
        "id": 405540902174720001,
        "rank":"SR.Moderator"
    },
    {
        "name": "Olexorus",
        "id": 210716756778418187,
        "rank": "Admin"
    },
    {
        "name": "Orthon",
        "id": 288374565170708480,
        "rank": "Moderator"
    },
    {
        "name": "PixelAnxiety",
        "id": 565544573154230313,
        "rank": "Helper"
    },
    {
        "name": "QAelin",
        "id": 692153466428063825,
        "rank": "Helper"
    },
    {
        "name": "Sebas",
        "id": 604994391995580470,
        "rank":"SR.Moderator"
    },
    {
        "name": "SivanEnnair",
        "id": 570952544709378049,
        "rank":"SR.Moderator"
    },
    {
        "name": "Sundroid",
        "id": 255766501464735744,
        "rank": "Owner"
    },
    {
        "name": "Tec",
        "id": 546277533138550786,
        "rank": "SR.Moderator"
    },
    {
        "name": "Tom",
        "id": 203577381385011200,
        "rank": "Admin"
    },
    {
        "name": "Yadiel",
        "id": 773685606622429184,
        "rank": "Moderator"
    }
]